uk_postcode_validator/__init__.py
uk_postcode_validator/client.py
uk_postcode_validator/tests.py
uk_postcode_validator-1.0.3.dist-info/METADATA
uk_postcode_validator-1.0.3.dist-info/RECORD
uk_postcode_validator-1.0.3.dist-info/WHEEL
uk_postcode_validator-1.0.3.dist-info/top_level.txt
