Metadata-Version: 2.1
Name: uk-postcode-validator
Version: 1.0.3
Summary: A Python wrapper for Postcodes.io to validate and format UK postcodes.
Home-page: UNKNOWN
Author: Jayakrishnan Damodaran
Author-email: jayakrishnandamodaran@gmail.com
License: MIT
Requires-Dist: requests (>=2.18.4)
